engineio/__init__.py
engineio/async_client.py
engineio/async_server.py
engineio/async_socket.py
engineio/base_client.py
engineio/base_server.py
engineio/base_socket.py
engineio/client.py
engineio/exceptions.py
engineio/json.py
engineio/middleware.py
engineio/packet.py
engineio/payload.py
engineio/server.py
engineio/socket.py
engineio/static_files.py
engineio/async_drivers/__init__.py
engineio/async_drivers/_websocket_wsgi.py
engineio/async_drivers/aiohttp.py
engineio/async_drivers/asgi.py
engineio/async_drivers/eventlet.py
engineio/async_drivers/gevent.py
engineio/async_drivers/gevent_uwsgi.py
engineio/async_drivers/sanic.py
engineio/async_drivers/threading.py
engineio/async_drivers/tornado.py
python_engineio-4.10.1.dist-info/LICENSE
python_engineio-4.10.1.dist-info/METADATA
python_engineio-4.10.1.dist-info/WHEEL
python_engineio-4.10.1.dist-info/top_level.txt
python_engineio-4.10.1.dist-info/RECORD
